Metadata-Version: 2.1
Name: cloudeos
Version: 0.1.1
Summary: https://cloudeos.com api sdk
Home-page: https://github.com/hknyldz/CloudeosApi
Author: Cloudeos
Author-email: team@cloudeos.com
License: UNKNOWN
Keywords: cloud,cloudeos
Platform: UNKNOWN
Classifier: Programming Language :: Python :: 3
Classifier: License :: OSI Approved :: MIT License
Classifier: Operating System :: OS Independent
Requires-Python: >=3.5
